{"version":"0.5.4","commands":{"build":{"id":"build","description":"Build the datapack. ⛏","pluginName":"sandstone-cli","pluginType":"core","aliases":[],"examples":["$ sand build","$ sand build --verbose","$ sand build --verbose --dry"],"flags":{"help":{"name":"help","type":"boolean","char":"h","description":"show CLI help","allowNo":false},"dry":{"name":"dry","type":"boolean","char":"d","description":"Do not save the datapack. Mostly useful with `verbose`.","allowNo":false},"verbose":{"name":"verbose","type":"boolean","char":"v","description":"Log all resulting resources: functions, advancements...","allowNo":false},"namespace":{"name":"namespace","type":"option","description":"The default namespace. Override the value specified in the configuration file."},"world":{"name":"world","type":"option","description":"The world to save the data pack in. Override the value specified in the configuration file."},"root":{"name":"root","type":"boolean","description":"Save the data pack in the `.minecraft/datapacks` folder. Override the value specified in the configuration file.","allowNo":false},"path":{"name":"path","type":"option","description":"The path to save the data pack at. Override the value specified in the configuration file."},"minecraftPath":{"name":"minecraftPath","type":"option","description":"Path of the .minecraft folder. Override the value specified in the configuration file."},"name":{"name":"name","type":"option","description":"Name of the data pack. Override the value specified in the configuration file."},"description":{"name":"description","type":"option","description":"Description of the data pack. Override the value specified in the configuration file."},"formatVersion":{"name":"formatVersion","type":"option","description":"Pack format version. Override the value specified in the configuration file."},"fullTrace":{"name":"fullTrace","type":"boolean","description":"Show the full stack trace on errors.","allowNo":false},"strictErrors":{"name":"strictErrors","type":"boolean","description":"Stop data pack compilation on type errors.","allowNo":false},"production":{"name":"production","type":"boolean","char":"p","description":"Runs Sandstone in production mode. This sets process.env.SANDSTONE_ENV to \"production\".","allowNo":false},"autoReload":{"name":"autoReload","type":"option","description":"Automatically reload your data pack in-game. Requires to open the world to LAN with cheats enabled, and to specify the port.","helpValue":"port"}},"args":[{"name":"path","description":"Path of the folder containing source files.","required":true,"default":"./src"},{"name":"config-path","description":"Path of the sandstone.config.ts folder.","required":true,"default":"."}]},"create":{"id":"create","description":"Create a new Sandstone project.","pluginName":"sandstone-cli","pluginType":"core","aliases":[],"examples":["$ sand create my-datapack"],"flags":{"help":{"name":"help","type":"boolean","char":"h","description":"show CLI help","allowNo":false},"yarn":{"name":"yarn","type":"boolean","description":"Use yarn instead of npm.","allowNo":false},"npm":{"name":"npm","type":"boolean","description":"Use npm.","allowNo":false},"datapack-name":{"name":"datapack-name","type":"option","char":"d","description":"The name of the data pack."},"namespace":{"name":"namespace","type":"option","char":"n","description":"The default namespace that will be used."},"save-root":{"name":"save-root","type":"boolean","char":"r","description":"Save the data pack in the .minecraft/datapacks folder. Not compatible with --world and --custom-path.","allowNo":false},"world":{"name":"world","type":"option","char":"w","description":"The world to save the data pack in. Not compatible with --save-root and --custom-path."},"custom-path":{"name":"custom-path","type":"option","char":"p","description":"The path to save the data pack at. Not compatible with --save-root and --world."}},"args":[{"name":"project-name","description":"Name of the project folder. This is not the name of the data pack.","required":true}]},"update":{"id":"update","description":"Update Sandstone & Sandstone-CLI.","pluginName":"sandstone-cli","pluginType":"core","aliases":[],"examples":["$ sand update","$ sand update --cli","$ sand update --sandstone","$ sand update --cli --sandstone --skip"],"flags":{"help":{"name":"help","type":"boolean","char":"h","description":"show CLI help","allowNo":false},"cli":{"name":"cli","type":"boolean","description":"Update the Sandstone CLI without asking.","allowNo":false},"sandstone":{"name":"sandstone","type":"boolean","description":"Update the current Sandstone version without asking.","allowNo":false},"skip":{"name":"skip","type":"boolean","description":"Skip all interactive prompts and refuse them.","allowNo":false},"yarn":{"name":"yarn","type":"boolean","description":"Use yarn to install the updates.","allowNo":false},"npm":{"name":"npm","type":"boolean","description":"Use npm to install the updates.","allowNo":false}},"args":[]},"watch":{"id":"watch","description":"Build the datapack, and rebuild it on file change. ⛏","pluginName":"sandstone-cli","pluginType":"core","aliases":[],"examples":["$ sand watch","$ sand watch --verbose","$ sand watch --verbose --dry"],"flags":{"help":{"name":"help","type":"boolean","char":"h","description":"show CLI help","allowNo":false},"dry":{"name":"dry","type":"boolean","char":"d","description":"Do not save the datapack. Mostly useful with `verbose`.","allowNo":false},"verbose":{"name":"verbose","type":"boolean","char":"v","description":"Log all resulting resources: functions, advancements...","allowNo":false},"namespace":{"name":"namespace","type":"option","description":"The default namespace. Override the value specified in the configuration file."},"world":{"name":"world","type":"option","description":"The world to save the data pack in. Override the value specified in the configuration file."},"root":{"name":"root","type":"boolean","description":"Save the data pack in the `.minecraft/datapacks` folder. Override the value specified in the configuration file.","allowNo":false},"path":{"name":"path","type":"option","description":"The path to save the data pack at. Override the value specified in the configuration file."},"minecraftPath":{"name":"minecraftPath","type":"option","description":"Path of the .minecraft folder. Override the value specified in the configuration file."},"name":{"name":"name","type":"option","description":"Name of the data pack. Override the value specified in the configuration file."},"description":{"name":"description","type":"option","description":"Description of the data pack. Override the value specified in the configuration file."},"formatVersion":{"name":"formatVersion","type":"option","description":"Pack format version. Override the value specified in the configuration file."},"fullTrace":{"name":"fullTrace","type":"boolean","description":"Show the full stack trace on errors.","allowNo":false},"strictErrors":{"name":"strictErrors","type":"boolean","description":"Stop data pack compilation on type errors.","allowNo":false},"production":{"name":"production","type":"boolean","char":"p","description":"Runs Sandstone in production mode. This sets process.env.SANDSTONE_ENV to \"production\".","allowNo":false},"autoReload":{"name":"autoReload","type":"option","description":"Automatically reload your data pack in-game. Requires to open the world to LAN with cheats enabled, and to specify the port.","helpValue":"port"}},"args":[{"name":"path","description":"Path of the folder containing source files.","required":true,"default":"./src"},{"name":"config-path","description":"Path of the sandstone.config.ts folder.","required":true,"default":"."}]}}}